{
  "schema_id": "orgsmith/docir@1",
  "doc_id": "d:0012",
  "blocks": [
    {
      "kind": "heading",
      "text": "Meeting Minutes: Transaction Readiness Review for Nguyen, Reynolds and Martinez",
      "level": 1,
      "items": [],
      "header": [],
      "rows": [],
      "signers": []
    },
    {
      "kind": "paragraph",
      "text": "Working session on the {{fact:f:E-2022-001.client}} readiness engagement, held by video conference. Minutes prepared by Briana Dennis; corrections by Friday, after which these stand as written.",
      "level": 1,
      "items": [],
      "header": [],
      "rows": [],
      "signers": []
    },
    {
      "kind": "heading",
      "text": "Attendees",
      "level": 2,
      "items": [],
      "header": [],
      "rows": [],
      "signers": []
    },
    {
      "kind": "list",
      "text": "",
      "level": 1,
      "items": [
        "Sandra Perez, Director, Fernhollow Partners LLC",
        "Briana Dennis, Senior Associate, Fernhollow Partners LLC",
        "Ryan Strong, Analyst, Fernhollow Partners LLC",
        "Amanda Golden, VP Finance, Nguyen, Reynolds and Martinez"
      ],
      "header": [],
      "rows": [],
      "signers": []
    },
    {
      "kind": "heading",
      "text": "Discussion",
      "level": 2,
      "items": [],
      "header": [],
      "rows": [],
      "signers": []
    },
    {
      "kind": "paragraph",
      "text": "Sandra Perez opened on the remediation log. The ranked items are down to a short tail, and nothing remaining touches the core financial statements. Ryan Strong walked through the state of the data room: the index is stable, and the latest document batch from the client loaded cleanly against it. Amanda Golden confirmed her team can turn the last schedule requests within the week.",
      "level": 1,
      "items": [],
      "header": [],
      "rows": [],
      "signers": []
    },
    {
      "kind": "paragraph",
      "text": "The back half of the session covered management preparation. Amanda Golden asked that the diligence-question sessions run before her quarter-end close, and Sandra Perez agreed to compress the schedule rather than split it. The written readiness assessment will follow the sessions, so its findings reflect how management actually answers, not only what the room contains.",
      "level": 1,
      "items": [],
      "header": [],
      "rows": [],
      "signers": []
    },
    {
      "kind": "heading",
      "text": "Action Items",
      "level": 2,
      "items": [],
      "header": [],
      "rows": [],
      "signers": []
    },
    {
      "kind": "list",
      "text": "",
      "level": 1,
      "items": [
        "Amanda Golden: return the remaining schedule requests to Ryan Strong within the week",
        "Sandra Perez: circulate the compressed plan for the management preparation sessions",
        "Ryan Strong: freeze the data room index and log any late additions separately",
        "Briana Dennis: outline the readiness assessment so drafting starts the day the sessions end"
      ],
      "header": [],
      "rows": [],
      "signers": []
    }
  ]
}
