{
  "schema_id": "orgsmith/engagements@1",
  "slug": "hollowell-ip",
  "engagements": [
    {
      "id": "E-2019-001",
      "title": "Patent Portfolio Review for Odonnell Inc",
      "client": "x:odonnell-inc",
      "start": "2019-05-13",
      "end": "2019-12-12",
      "fee": 120000,
      "internal_participants": [
        "p:kelly.snyder",
        "p:amanda.schwartz",
        "p:heather.munoz"
      ],
      "external_participants": [
        "xp:gary.smith"
      ],
      "summary": "Patent Portfolio Review engagement for Odonnell Inc, running May 2019 through December 2019 at a fixed fee of $120,000.",
      "facts": [
        {
          "id": "f:E-2019-001.fee",
          "kind": "money",
          "value": 120000,
          "rendered": "$120,000",
          "location_policy": "signature_page"
        },
        {
          "id": "f:E-2019-001.start",
          "kind": "date",
          "value": "2019-05-13",
          "rendered": "May 13, 2019",
          "location_policy": "body"
        },
        {
          "id": "f:E-2019-001.client",
          "kind": "text",
          "value": "Odonnell Inc",
          "rendered": "Odonnell Inc",
          "location_policy": "body"
        }
      ]
    },
    {
      "id": "E-2020-001",
      "title": "Freedom-to-Operate Analysis for Middleton, Sullivan and Wiley",
      "client": "x:middleton-sullivan-and-wiley",
      "start": "2020-05-12",
      "end": "2021-01-24",
      "fee": 113500,
      "internal_participants": [
        "p:richard.henderson",
        "p:kelly.snyder",
        "p:heather.munoz"
      ],
      "external_participants": [
        "xp:barbara.blair"
      ],
      "summary": "Freedom-to-Operate Analysis engagement for Middleton, Sullivan and Wiley, running May 2020 through January 2021 at a fixed fee of $113,500.",
      "facts": [
        {
          "id": "f:E-2020-001.fee",
          "kind": "money",
          "value": 113500,
          "rendered": "$113,500",
          "location_policy": "body"
        },
        {
          "id": "f:E-2020-001.start",
          "kind": "date",
          "value": "2020-05-12",
          "rendered": "May 12, 2020",
          "location_policy": "body"
        },
        {
          "id": "f:E-2020-001.client",
          "kind": "text",
          "value": "Middleton, Sullivan and Wiley",
          "rendered": "Middleton, Sullivan and Wiley",
          "location_policy": "body"
        }
      ]
    },
    {
      "id": "E-2021-001",
      "title": "Prosecution Support for Keith-Duarte",
      "client": "x:keith-duarte",
      "start": "2021-08-11",
      "end": "2022-01-16",
      "fee": 39500,
      "internal_participants": [
        "p:heather.munoz",
        "p:kelly.snyder",
        "p:joseph.walker"
      ],
      "external_participants": [
        "xp:joseph.palmer"
      ],
      "summary": "Prosecution Support engagement for Keith-Duarte, running August 2021 through January 2022 at a fixed fee of $39,500.",
      "facts": [
        {
          "id": "f:E-2021-001.fee",
          "kind": "money",
          "value": 39500,
          "rendered": "$39,500",
          "location_policy": "body"
        },
        {
          "id": "f:E-2021-001.start",
          "kind": "date",
          "value": "2021-08-11",
          "rendered": "August 11, 2021",
          "location_policy": "body"
        },
        {
          "id": "f:E-2021-001.client",
          "kind": "text",
          "value": "Keith-Duarte",
          "rendered": "Keith-Duarte",
          "location_policy": "body"
        }
      ]
    },
    {
      "id": "E-2024-001",
      "title": "Trademark Clearance for Jackson Inc",
      "client": "x:jackson-inc",
      "start": "2024-04-09",
      "end": "2024-08-03",
      "fee": 48000,
      "internal_participants": [
        "p:ashley.williams",
        "p:kelly.snyder"
      ],
      "external_participants": [
        "xp:cynthia.hunter"
      ],
      "summary": "Trademark Clearance engagement for Jackson Inc, running April 2024 through August 2024 at a fixed fee of $48,000.",
      "facts": [
        {
          "id": "f:E-2024-001.fee",
          "kind": "money",
          "value": 48000,
          "rendered": "$48,000",
          "location_policy": "body"
        },
        {
          "id": "f:E-2024-001.start",
          "kind": "date",
          "value": "2024-04-09",
          "rendered": "April 9, 2024",
          "location_policy": "body"
        },
        {
          "id": "f:E-2024-001.client",
          "kind": "text",
          "value": "Jackson Inc",
          "rendered": "Jackson Inc",
          "location_policy": "body"
        }
      ]
    },
    {
      "id": "E-2025-001",
      "title": "Licensing Diligence for Price-Henson",
      "client": "x:price-henson",
      "start": "2025-03-14",
      "end": "2025-09-02",
      "fee": 41000,
      "internal_participants": [
        "p:david.chang",
        "p:richard.henderson"
      ],
      "external_participants": [
        "xp:tiffany.munoz"
      ],
      "summary": "Licensing Diligence engagement for Price-Henson, running March 2025 through September 2025 at a fixed fee of $41,000.",
      "facts": [
        {
          "id": "f:E-2025-001.fee",
          "kind": "money",
          "value": 41000,
          "rendered": "$41,000",
          "location_policy": "body"
        },
        {
          "id": "f:E-2025-001.start",
          "kind": "date",
          "value": "2025-03-14",
          "rendered": "March 14, 2025",
          "location_policy": "body"
        },
        {
          "id": "f:E-2025-001.client",
          "kind": "text",
          "value": "Price-Henson",
          "rendered": "Price-Henson",
          "location_policy": "body"
        }
      ]
    }
  ]
}
