{
  "schema_id": "orgsmith/docir@1",
  "doc_id": "d:0142",
  "blocks": [
    {
      "kind": "paragraph",
      "text": "Working session on the Capital Allocation Review for {{fact:f:E-2019-003.client}}. Minutes recorded by Deborah Jimenez.",
      "level": 1,
      "items": [],
      "header": [],
      "rows": [],
      "signers": []
    },
    {
      "kind": "heading",
      "text": "Present",
      "level": 2,
      "items": [],
      "header": [],
      "rows": [],
      "signers": []
    },
    {
      "kind": "list",
      "text": "",
      "level": 1,
      "items": [
        "Deborah Jimenez, Engagement Manager",
        "Brenda Clayton, Consultant",
        "Sandra Flores, Chief Operating Officer, Poole, Mcknight and Rush"
      ],
      "header": [],
      "rows": [],
      "signers": []
    },
    {
      "kind": "heading",
      "text": "Discussion",
      "level": 2,
      "items": [],
      "header": [],
      "rows": [],
      "signers": []
    },
    {
      "kind": "paragraph",
      "text": "The session reviewed the current-state work. Brenda Clayton presented the process map: how a capital request is raised, evaluated, approved, and funded within the business. The map is largely complete. One step is thinly documented, the post-investment review, because it appears to happen rarely and without a standard record. Where the practice is inconsistent the map shows the range rather than a single path. Brenda Clayton walked the group through two units whose steps differ enough that a request of the same size follows a noticeably different path in each.",
      "level": 1,
      "items": [],
      "header": [],
      "rows": [],
      "signers": []
    },
    {
      "kind": "paragraph",
      "text": "The criteria used to weigh requests are not applied uniformly. Some units test a request against a hurdle rate; others do not. The spending threshold that sends a request to committee differs from one unit to the next. This is recorded as an observation. It is not yet a recommendation, and nothing in it should be read as one at this stage. Brenda Clayton noted that the divergence itself is the useful finding, since it explains why comparable requests fare differently depending on where they originate.",
      "level": 1,
      "items": [],
      "header": [],
      "rows": [],
      "signers": []
    },
    {
      "kind": "paragraph",
      "text": "Deborah Jimenez confirmed the units in scope with Sandra Flores, so the review covers the parts of the business the engagement letter named and no others. The team also agreed that data requests to the client will route through a single point of contact. Sending the same question to several people had already produced two answers that did not match, and a single route avoids that.",
      "level": 1,
      "items": [],
      "header": [],
      "rows": [],
      "signers": []
    },
    {
      "kind": "paragraph",
      "text": "The spending history is assembled for recent years and split by purpose and by unit. One unit's records are incomplete. Sandra Flores agreed to have the missing files sent over. Until they arrive, the combined history carries a gap in that unit and no firm total. Deborah Jimenez asked that the gap be marked plainly in any interim material so it is not mistaken for a complete figure.",
      "level": 1,
      "items": [],
      "header": [],
      "rows": [],
      "signers": []
    },
    {
      "kind": "paragraph",
      "text": "Sandra Flores asked for an early read on the size of the savings the review might find. Brenda Clayton declined to give one. The figure depends on the criteria work, which is not finished, and any number offered now would not hold. The group agreed to revisit the question once that work is drafted, rather than attach a figure the analysis cannot yet support.",
      "level": 1,
      "items": [],
      "header": [],
      "rows": [],
      "signers": []
    },
    {
      "kind": "heading",
      "text": "Action items",
      "level": 2,
      "items": [],
      "header": [],
      "rows": [],
      "signers": []
    },
    {
      "kind": "table",
      "text": "",
      "level": 1,
      "items": [],
      "header": [
        "Action",
        "Owner",
        "Due"
      ],
      "rows": [
        [
          "Send the missing unit's capital records",
          "Sandra Flores",
          "Within two weeks"
        ],
        [
          "Complete the current-state process map, including the post-investment review step",
          "Brenda Clayton",
          "Before the next session"
        ],
        [
          "Reconcile the spending history once the missing records arrive",
          "Brenda Clayton",
          "Before the next session"
        ],
        [
          "Confirm the committee thresholds in force in each unit",
          "Sandra Flores",
          "Within two weeks"
        ],
        [
          "Set the next working session once the criteria assessment is drafted",
          "Deborah Jimenez",
          "On completion"
        ]
      ],
      "signers": []
    }
  ]
}
